Metadata-Version: 1.0
Name: probality-dist-valmapaura
Version: 1.0.0
Summary: Gaussian and Binomial distributions
Home-page: UNKNOWN
Author: Valentine Mapaura
Author-email: valmapaura@gmail.com
License: UNKNOWN
Platform: UNKNOWN
